django_FBO/__init__.py
django_FBO/__script__.py
django_FBO/baking.py
django_FBO/file_objects.py
django_FBO/manager.py
django_FBO/query.py
django_FBO/management/__init__.py
django_FBO/management/commands/__init__.py
django_FBO/management/commands/bake_site.py
django_FBO/modules/__init__.py
django_FBO/modules/binary.py
django_FBO/modules/blog.py
django_FBO/modules/interspersed.py
django_FBO/modules/pages.py
django_FBO/site_templates/manage.py
django_FBO/site_templates/requirements.txt
django_FBO/site_templates/settings.py
django_FBO/site_templates/urls.py
django_FBO/site_templates/wsgi.py
django_FBO/site_templates/static/css/style.css
django_FBO/site_templates/templates/base.html
django_FBO/site_templates/templates/home.html
django_FBO/site_templates/templates/page.html
django_FBO/site_templates/templates/blog/_pagination.html
django_FBO/site_templates/templates/blog/draft.html
django_FBO/site_templates/templates/blog/index.html
django_FBO/site_templates/templates/blog/post.html
django_FBO-4.1.0.dist-info/METADATA
django_FBO-4.1.0.dist-info/WHEEL
django_FBO-4.1.0.dist-info/entry_points.txt
django_FBO-4.1.0.dist-info/top_level.txt
django_FBO-4.1.0.dist-info/RECORD
