Metadata-Version: 2.1
Name: django-FBO
Version: 4.1.0
Summary: Access file-backed objects in something resembling the ORM.
Home-page: https://github.com/jaylett/django-filebacked-objects
Author: James Aylett
Author-email: james@tartarus.org
License: MIT
Platform: UNKNOWN
Classifier: Intended Audience :: Developers
Classifier: Framework :: Django
Classifier: License :: OSI Approved :: MIT License
Classifier: Programming Language :: Python :: 3
Requires-Dist: Django (>=2.1.0)
Requires-Dist: PyYAML (~=5.3.1)
